jcclang/__init__.py
jcclang/adapter/__init__.py
jcclang/adapter/base_adapter.py
jcclang/adapter/modelarts.py
jcclang/adapter/octopus.py
jcclang/adapter/openi.py
jcclang/api/__init__.py
jcclang/api/context.py
jcclang/api/data_prepare.py
jcclang/api/decorators.py
jcclang/api/jobhub.py
jcclang/api/jobhub_api.py
jcclang/api/jobhub_api2.py
jcclang/api/data_loader/llama_loader.py
jcclang/api/data_loader/pandas_loader.py
jcclang/api/data_loader/tensorflow_loader.py
jcclang/api/data_loader/torch_loader.py
jcclang/api/data_loader/transformers_loader.py
jcclang/api/data_loader/transformers_hook/vfile_io2.py
jcclang/api/data_loader/transformers_hook/virtual_file_io.py
jcclang/core/__init__.py
jcclang/core/const.py
jcclang/core/context.py
jcclang/core/logger.py
jcclang/core/metadata.py
jcclang/core/model.py
jcclang/core/registry.py
jcclang/core/schema.py
jcclang/core/io/__init__.py
jcclang/core/io/abc.py
jcclang/core/io/chunked.py
jcclang/core/io/ext.py
jcclang/core/io/utils.py
jcclang/core/jobhub/__init__.py
jcclang/core/jobhub/abc.py
jcclang/core/jobhub/exceptions.py
jcclang/core/jobhub/jobhub.py
jcclang/core/jobhub/rpc.py
jcclang/core/jobhub/types.py
jcclang/core/jobhub/utils.py
jcclang/core/jobhub/yamux/__init__.py
jcclang/core/jobhub/yamux/exceptions.py
jcclang/core/jobhub/yamux/yamux.py
jcclang/core/utils/__init__.py
jcclang/core/utils/args_mapping.py
jcclang/core/utils/presign.py
jcclang/core/utils/presign_test.py
jcclang/core/utils/rw_lock.py
jcclang/examples/__init__.py
jcclang/examples/data_loader/llama_streaming.py
jcclang/examples/data_loader/pandas_demo.py
jcclang/examples/data_loader/pt_emnist.py
jcclang/examples/data_loader/pt_llama.py
jcclang/examples/data_loader/pt_llama_hook.py
jcclang/examples/data_loader/pt_mnist.py
jcclang/examples/data_loader/pt_mnist2.py
jcclang/examples/data_loader/pt_mnist_dirct.py
jcclang/examples/data_loader/tf_demo.py
jcclang/examples/data_prepare/__init__.py
jcclang/examples/data_prepare/data_preprocess.py
jcclang-0.1.4.dist-info/METADATA
jcclang-0.1.4.dist-info/WHEEL
jcclang-0.1.4.dist-info/top_level.txt
jcclang-0.1.4.dist-info/RECORD
