Metadata-Version: 2.4
Name: jcclang
Version: 0.1.4
Summary: A platform-adaptive task framework for cloud-edge scenarios
Author-email: jeshua <ren1366929814@gmail.com>
Classifier: Programming Language :: Python :: 3
Classifier: Operating System :: OS Independent
Requires-Python: >=3.7
